[
    {
        "id": 1,
        "todo": "勉強する"
    },
    {
        "id": 2,
        "todo": "寝る"
    },
    {
        "id": 3,
        "todo": "運動する"
    },
    {
        "id": 4,
        "todo": "企業する"
    },
    {
        "id": 5,
        "todo": "食べる"
    },
    {
        "id": 6,
        "todo": "勉強する"
    },
    {
        "id": 7,
        "todo": "陸上する"
    },
    {
        "id": 8,
        "todo": "酒を飲む"
    },
    {
        "id": 9,
        "todo": "仕事辞める"
    },
    {
        "id": 10,
        "todo": "散歩する"
    },
    {
        "id": 11,
        "todo": "アプリ作る"
    }
]